<?xml version="1.0" encoding="WINDOWS-1252"?>
<!-- Generated by Oracle Reports version 10.1.2.0.2 -->
<XXRPOP2P>
  <LIST_G_OPERATING_UNIT>
    <G_OPERATING_UNIT>
      <PO_HEADER_ID>272216</PO_HEADER_ID>
      <Operating_unit>SV_TELEMOVIL_OU</Operating_unit>
      <Vendor_name>PYRUS, S. A. DE C. V.</Vendor_name>
      <Vendor_site_code>SV_LOC</Vendor_site_code>
      <Currency_code>USD</Currency_code>
      <Revision_num>0</Revision_num>
      <Release_number></Release_number>
      <Authorization_status>APPROVED</Authorization_status>
      <Approved_date>06/12/2013</Approved_date>
      <CAR>SV1334</CAR>
      <Line_number>1</Line_number>
      <Description>BATTERIES</Description>
      <Unit_price>496.159</Unit_price>
      <Cancel_flag></Cancel_flag>
      <Cancel_reason></Cancel_reason>
      <Shipment_number>1</Shipment_number>
      <Need_by_date>20/12/2013</Need_by_date>
      <Quantity_received>560</Quantity_received>
      <Organization_name>SV_S14_TELEMOVIL_BODEGA TURNKEY</Organization_name>
      <Destination_subinventory></Destination_subinventory>
      <Invoice_amount>313969.42</Invoice_amount>
      <Terms_date>10-DEC-13</Terms_date>
      <Payment_terms>NET 45</Payment_terms>
      <Payment_number>4780</Payment_number>
      <Payment_date>20-DEC-13</Payment_date>
      <Position_hierarchy_name>SV_PO_TELEMOVIL_TECHNOLOGY FAC</Position_hierarchy_name>
      <Line_type>Goods</Line_type>
      <Promised_date>20/12/2013</Promised_date>
      <SOLICITANTE>MENDOZA MORALESDE, VICTOR HUGO</SOLICITANTE>
      <NUMERO_SOLICITUD>4837</NUMERO_SOLICITUD>
      <FECHA_SOLICITUD>29/11/2013</FECHA_SOLICITUD>
      <FECHA_APROBACION_SOLICITUD>02/12/2013</FECHA_APROBACION_SOLICITUD>
      <TERMINOS_PAGO>NET 45</TERMINOS_PAGO>
      <NUMERO_PO>4696</NUMERO_PO>
      <PO_DESCRIPTION>&quot;REPROCESO&quot; ESTA PO SUSTITUYE A LA PO 3905 CORRESPONDIENTE A LA COMPRA DE BATERIAS ENERSYS PARA 2DA FASE DE REEMPLAZO DE BANCOS DE BATERIAS</PO_DESCRIPTION>
      <CLOSED_CODE>CLOSED</CLOSED_CODE>
      <FECHA_ORDEN>02/12/2013</FECHA_ORDEN>
      <COMPRADOR>LARA BANOS, OMAR ERNESTO</COMPRADOR>
      <FORMA_COMPRA>CONTRACT</FORMA_COMPRA>
      <TIPO_COMPRA>CAPEX</TIPO_COMPRA>
      <TERMINOS_FACTURAION>CONTRA ENTREGA</TERMINOS_FACTURAION>
      <MONTO_AHORRO>21261.00</MONTO_AHORRO>
      <DETALLE_AHORRO>SE LOGRO QUE EL PROVEEDOR MANTUVIERA EL PRECIO DE LA FASE I PARA EL SUMINISTRO E INSTALACION DE BATERIAS</DETALLE_AHORRO>
      <CODIGO_ITEM>ADM0000100</CODIGO_ITEM>
      <CATEGORY_SEGMENTS>00-00-00-00</CATEGORY_SEGMENTS>
      <CATEGORY_DESCRIPTION>General-General-General-General</CATEGORY_DESCRIPTION>
      <NOTE_TO_VENDOR>Suministro e instalacion de baterias Enersys de 12 voltios, plomo puro, libres de mtto, biodegaje de baterias desinstaladas por 3 meses.</NOTE_TO_VENDOR>
      <CANTIDAD>560</CANTIDAD>
      <MONTO>277849.04</MONTO>
      <CANTIDAD_PENDIENTE>0</CANTIDAD_PENDIENTE>
      <MONTO_PENDIENTE>0</MONTO_PENDIENTE>
      <MONTO_RECIBIDO>277849.04</MONTO_RECIBIDO>
      <QUANTITY_BILLED>560</QUANTITY_BILLED>
      <AMOUNT_BILLED>277849.04</AMOUNT_BILLED>
      <FLEXFIELD_CONTABLE>1SV001.12021101.00000000.00000.000.000.00.000.SV1334.000000.017.00000.00000</FLEXFIELD_CONTABLE>
      <NUMERO_FACTURA>212</NUMERO_FACTURA>
      <FECHA_FACTURA>06-DEC-13</FECHA_FACTURA>
      <FECHA_PROGRAMADA_PAGO>24-JAN-14</FECHA_PROGRAMADA_PAGO>
      <USUARIO_FACTURACION>MARBUES@SV.TIGO.COM</USUARIO_FACTURACION>
      <MONTO_PAGADO>311190.93</MONTO_PAGADO>
      <PAYMENT_USER>JPASTOR@SV.TIGO.COM</PAYMENT_USER>
      <CF_RECEIPT_NUM>327, 3278, 3183</CF_RECEIPT_NUM>
	  <CF_RECEIPT_DATE>01/01/2014, 01/02/2014, 01/03.22014</CF_RECEIPT_DATE>
      <Exchange_rate>1</Exchange_rate>
    </G_OPERATING_UNIT>
  </LIST_G_OPERATING_UNIT>
  <CP_ITEM> AND 1 = 1 </CP_ITEM>
  <CP_CENCOSTO> AND 2 = 2 </CP_CENCOSTO>
  <CP_CAR> AND 3 = 3 </CP_CAR>
  <CP_CUENTA> AND 4 = 4 </CP_CUENTA>
  <CP_PERSON_ID> AND 5 = 5 </CP_PERSON_ID>
  <CP_VENDOR_ID> AND 6 = 6 </CP_VENDOR_ID>
  <CP_REQUESTER> AND 7 = 7 </CP_REQUESTER>
  <CP_PO_NUMBERS> AND 8 = 8 </CP_PO_NUMBERS>
  <CP_MONTO></CP_MONTO>
  <CP_TIPO_COMPRA> AND 9 = 9 </CP_TIPO_COMPRA>
</XXRPOP2P>
